slackformat/__init__.py
slackformat/converters/__init__.py
slackformat/converters/blockkit_to_md.py
slackformat/converters/blockkit_to_richtext.py
slackformat/converters/md_to_blockkit.py
slackformat/converters/md_to_richtext.py
slackformat/converters/richtext_to_blockkit.py
slackformat/converters/richtext_to_md.py
slackformat/core/__init__.py
slackformat/core/base_converter.py
slackformat/core/exceptions.py
slackformat/core/validation.py
slackformat/formatters/__init__.py
slackformat/formatters/link_formatter.py
slackformat/formatters/list_formatter.py
slackformat/formatters/text_formatter.py
slackformat/parsers/__init__.py
slackformat/parsers/blockkit_parser.py
slackformat/parsers/markdown_parser.py
slackformat/parsers/richtext_parser.py
slackformat/utils/__init__.py
slackformat/utils/merge_utils.py
slackformat/utils/style_utils.py
slackformat/utils/text_utils.py
slackformat-1.0.0.dist-info/licenses/LICENSE
slackformat-1.0.0.dist-info/METADATA
slackformat-1.0.0.dist-info/WHEEL
slackformat-1.0.0.dist-info/top_level.txt
slackformat-1.0.0.dist-info/RECORD
