Metadata-Version: 2.4
Name: slackformat
Version: 1.0.0
Summary: A utility for converting between Slack's formats.
Author: Sam Begin
License-Expression: Apache-2.0
Project-URL: Homepage, https://github.com/sbegin0/SlackFormat
Project-URL: Repository, https://github.com/sbegin0/SlackFormat
Project-URL: Issues, https://github.com/sbegin0/SlackFormat/issues
Keywords: slack,markdown,block-kit,rich-text,converter
Classifier: Programming Language :: Python :: 3
Classifier: Programming Language :: Python :: 3 :: Only
Classifier: Programming Language :: Python :: 3.9
Classifier: Programming Language :: Python :: 3.10
Classifier: Programming Language :: Python :: 3.11
Classifier: Programming Language :: Python :: 3.12
Classifier: Operating System :: OS Independent
Classifier: Topic :: Text Processing :: Markup
Requires-Python: >=3.9
License-File: LICENSE
Dynamic: license-file
